certbot_dns_bookmyname/__init__.py
certbot_dns_bookmyname/__main__.py
certbot_dns_bookmyname/dns_bookmyname.py
certbot_dns_bookmyname-1.0.0.dist-info/LICENSE
certbot_dns_bookmyname-1.0.0.dist-info/METADATA
certbot_dns_bookmyname-1.0.0.dist-info/WHEEL
certbot_dns_bookmyname-1.0.0.dist-info/entry_points.txt
certbot_dns_bookmyname-1.0.0.dist-info/top_level.txt
certbot_dns_bookmyname-1.0.0.dist-info/RECORD
