Metadata-Version: 2.1
Name: certbot-dns-bookmyname
Version: 1.0.0
Summary: BookMyName DNS Authenticator plugin for Certbot
Author-email: Joffrey Darcq <j-off@live.fr>
License:    Copyright 2015 Electronic Frontier Foundation and others
Project-URL: Homepage, https://github.com/Joffr3y/certbot-dns-bookmyname
Project-URL: Repository, https://github.com/Joffr3y/certbot-dns-bookmyname.git
Project-URL: Issues, https://github.com/Joffr3y/certbot-dns-bookmyname/issues
Classifier: Development Status :: 5 - Production/Stable
Classifier: Environment :: Plugins
Classifier: Intended Audience :: System Administrators
Classifier: License :: OSI Approved :: Apache Software License
Classifier: Operating System :: POSIX :: Linux
Classifier: Programming Language :: Python
Classifier: Programming Language :: Python :: 3
Classifier: Programming Language :: Python :: 3.8
Classifier: Programming Language :: Python :: 3.9
Classifier: Programming Language :: Python :: 3.10
Classifier: Programming Language :: Python :: 3.11
Classifier: Programming Language :: Python :: 3.12
Classifier: Programming Language :: Python :: 3.13
Classifier: Topic :: Internet :: WWW/HTTP
Classifier: Topic :: Security
Classifier: Topic :: System :: Installation/Setup
Classifier: Topic :: System :: Networking
Classifier: Topic :: System :: Systems Administration
Classifier: Topic :: Utilities
Requires-Python: >=3.8
License-File: LICENSE
Requires-Dist: certbot
Requires-Dist: requests
Requires-Dist: setuptools
Provides-Extra: dev
Requires-Dist: python-lsp-server; extra == "dev"
Requires-Dist: pylsp-mypy; extra == "dev"
Provides-Extra: test
Requires-Dist: mypy; extra == "test"
Requires-Dist: pycodestyle; extra == "test"
Requires-Dist: pylint; extra == "test"
Requires-Dist: pytest; extra == "test"
Requires-Dist: types-requests; extra == "test"
